{
    "N级舰娘": [
        "{%常驻N级舰娘}"
    ],
    "R级舰娘": [
        "{%常驻R级舰娘}"
    ],
    "SR级舰娘": [
        "{%常驻SR级舰娘}"
    ],
    "SSR级舰娘": [
        "{%常驻SSR级舰娘}"
    ],
    "SR舰娘": [
        "朝潮级驱逐舰九番舰 霞 （蕸） IJN Kasumi 霞",
        "长良级轻巡洋舰五番舰 鬼怒 （猤） IJN Kinu 鬼怒",
        "{%常驻SR级舰娘}"
    ],
    "SSR级舰娘": [
        "阿贺野级轻型巡洋舰二番舰 能代 （貅） IJN Noshiro 能代", 
        "（轻型）航空母舰 龙凤 （鸗） IJN Ryūhō 龍鳳",
        "纪伊级战列舰三番舰 骏河 （鲪） IJN Suruga",
        "{%常驻SSR级舰娘}", 
        "{%常驻SSR级舰娘}", 
        "{%常驻SSR级舰娘}" 
    ],
    "常驻N级舰娘": [ 
        "B级驱逐舰 小猎兔犬 HMS Beagle ビーグル", 
        "B级驱逐舰 大斗犬 HMS Bulldog ブルドッグ", 
        "C级驱逐舰 新月 HMS Crescent クレセント", 
        "C级驱逐舰 小天鹅 HMS Cygnet シグニット", 
        "C级驱逐舰 彗星 HMS Comet コメット", 
        "睦月级驱逐舰一番舰 睦月 （松） IJN Mutsuki 睦月", 
        "睦月级驱逐舰二番舰 如月 （樟） IJN Kisaragi 如月", 
        "睦月级驱逐舰四番舰 卯月 （楙） IJN Uzuki 卯月", 
        "马汉级驱逐舰9号舰 卡辛 USS Cassin カッシン", 
        "马汉级驱逐舰12号舰 唐斯 USS Downes ダウンズ", 
        "F级驱逐舰 狐提 HMS Foxhound フォックスハウンド", 
        "格里德利级驱逐舰2号舰 克雷文 USS Craven クレイヴン", 
        "格里德利级驱逐舰3号舰 麦考尔 USS McCall マッコール", 
        "弗莱彻级驱逐舰85号舰 奥利克 USS Aulick オーリック", 
        "弗莱彻级驱逐舰34号舰 富特 USS Foote フート", 
        "弗莱彻级驱逐舰35号舰 斯彭斯 USS Spence スペンス", 
        "奥马哈级轻巡洋舰4号舰 罗利 USS Raleigh ローリー", 
        "奥马哈级轻巡洋舰1号舰 奥马哈 USS Omaha オマハ", 
        "长良级轻巡洋舰一番舰 长良 （貊） IJN Nagara 長良", 
        "柯尼斯堡级轻巡洋舰3号舰 科隆 KMS Köln ケルン", 
        "柯尼斯堡级轻巡洋舰1号舰 柯尼斯堡 KMS Königsberg ケーニヒスベルク", 
        "柯尼斯堡级轻巡洋舰2号舰 卡尔斯鲁厄 KMS Karlsruhe カールスルーエ", 
        "利安得级轻巡洋舰1号舰 利安得 HMS Leander リアンダー", 
        "彭萨科拉级重巡洋舰1号舰 彭萨科拉 USS Pensacola ペンサコーラ", 
        "青叶级重巡洋舰一番舰 青叶 （犹） IJN Aoba 青葉", 
        "青叶级重巡洋舰二番舰 衣笠 （猅） IJN Kinugasa 衣笠", 
        "（轻型）航空母舰 兰利 USS Langley ラングレー", 
        "（轻型）航空母舰 竞技神 HMS Hermes ハーミーズ", 
        "（轻型）航空母舰 突击者 USS Ranger レンジャー", 
        "内华达级战列舰的2号舰 俄克拉荷马 USS Oklahoma オクラホマ", 
        "内华达级战列舰的1号舰 内华达 USS Nevada ネバダ"  
    ],
    "常驻R级舰娘": [ 
        "A级实验型驱逐舰 女将 HMS Amazon アマゾン", 
        "A级驱逐舰 阿卡司塔 HMS Acasta アカスタ", 
        "A级驱逐舰 热心 HMS Ardent アーデント", 
        "神风级驱逐舰一番舰 神风 （榊） IJN Kamikaze 神風", 
        "神风级驱逐舰四番舰 松风 （棡） IJN Matsukaze 松風", 
        "F级驱逐舰 命运女神 HMS Fortune フォーチュン", 
        "初春级驱逐舰三番舰 若叶 （楉） IJN Wakaba 若葉", 
        "初春级驱逐舰一番舰 初春 （梅） IJN Hatsuharu 初春", 
        "初春级驱逐舰四番舰 初霜 （檨） IJN Hatsushimo 初霜", 
        "改初春级驱逐舰一番舰 有明 （榎） IJN Ariake 有明", 
        "改初春级驱逐舰二番舰 夕暮 （棭） IJN Yūgure 夕暮", 
        "西姆斯级驱逐舰4号舰 哈曼 USS Hammann ハムマン", 
        "J级驱逐舰 丘比特 HMS Jupiter ジュピター", 
        "J级驱逐舰 泽西 HMS Jersey ジャージー", 
        "本森级驱逐舰1号舰 本森 USS Benson ベンソン", 
        "本森级驱逐舰10号舰 贝利 USS Bailey ベイリー", 
        "阳炎级驱逐舰十四番舰 谷风 （栭） IJN Tanikaze 谷風", 
        "阳炎级驱逐舰十一番舰 浦风 （槆） IJN Urakaze 浦風", 
        "阳炎级驱逐舰十二番舰 矶风 （柉） IJN Isokaze 磯風", 
        "夕云级驱逐舰八番舰 清波 （棈） IJN Kiyonami 清波", 
        "弗莱彻级驱逐舰21号舰 斯坦利 USS Stanly スタンリー", 
        "弗莱彻级驱逐舰81号舰 斯莫利 USS Smalley スモーリー", 
        "弗莱彻级驱逐舰13号舰 贝奇 USS Bache バッチ", 
        "弗莱彻级驱逐舰37号舰 撒切尔 USS Thatcher サッチャー", 
        "弗莱彻级驱逐舰1号舰 弗莱彻 USS Fletcher フレッチャー", 
        "弗莱彻级驱逐舰49号舰 布什 USS Bush ブッシュ", 
        "朝潮级驱逐舰二番舰 大潮 （荙） IJN Ōshio 大潮", 
        "1936型驱逐舰 Z18 KMS Hans Lüdemann Z18", 
        "1936型驱逐舰 Z19 KMS Hermann Künne Z19", 
        "奥马哈级轻巡洋舰7号舰 康克德 USS Concord コンコード", 
        "奥马哈级轻巡洋舰10号舰 孟菲斯 USS Memphis メンフィス", 
        "谷物女神级轻巡洋舰 库拉索 HMS Curacoa キュラソー", 
        "谷物女神级轻巡洋舰 杓鹬 HMS Curlew カーリュー", 
        "亚特兰大级轻巡洋舰1号舰 亚特兰大 USS Atlanta アトランタ", 
        "亚特兰大级轻巡洋舰2号舰 朱诺 USS Juneau ジュノー", 
        "利安得级轻巡洋舰3号舰 阿贾克斯 HMS Ajax エイジャックス", 
        "布鲁克林级轻巡洋舰1号舰 布鲁克林 USS Brooklyn ブルックリン", 
        "布鲁克林级轻巡洋舰5号舰 菲尼克斯 USS Phoenix フェニックス", 
        "利安得级轻巡洋舰2号舰 阿基里斯 HMS Achilles アキリーズ", 
        "莱比锡级轻巡洋舰1号舰 莱比锡 KMS Leipzig ライプツィヒ", 
        "斐济级轻巡洋舰 牙买加 HMS Jamaica ジャマイカ", 
        "南安普顿级轻巡洋舰 南安普顿 HMS Southampton サウサンプトン", 
        "南安普顿级轻巡洋舰 格拉斯哥 HMS Glasgow グラスゴー", 
        "伦敦级重巡洋舰4号舰 什罗普郡 HMS Shropshire シュロップシャー", 
        "肯特级重巡洋舰1号舰 肯特 HMS Kent ケント", 
        "肯特级重巡洋舰5号舰 萨福克 HMS Suffolk サフォーク", 
        "诺福克级重巡洋舰1号舰 诺福克 HMS Norfolk ノーフォーク", 
        "伦敦级重型巡洋舰3号舰 苏塞克斯 HMS Sussex サセックス", 
        "北安普顿级重巡洋舰4号舰 芝加哥 USS Chicago シカゴ", 
        "北安普顿级重巡洋舰1号舰 北安普敦 USS Northampton ノーザンプトン", 
        "波特兰级重型巡洋舰1号舰 波特兰 USS Portland ポートランド", 
        "声望级战列巡洋舰2号舰 反击 HMS Repulse レパルス", 
        "宾夕法尼亚级战列舰1号舰 宾夕法尼亚 USS Pennsylvania ペンシルベニア", 
        "田纳西级战列舰2号舰 加利福尼亚 USS California カリフォルニア", 
        "田纳西级战列舰1号舰 田纳西 USS Tennessee テネシー", 
        "伊势级战列舰一番舰 伊势 （鳌） IJN Ise 伊勢", 
        "伊势级战列舰二番舰 日向 （螯） IJN Hyūga 日向" 
    ],
    "常驻SR级舰娘": [ 
        "VIIC型潜艇 U-557 KMS U-557", 
        "旧V级驱逐舰 吸血鬼 HMS Vampire ヴァンパイア", 
        "特I型吹雪级驱逐舰一番舰 吹雪 （桐） IJN Fubuki 吹雪", 
        "特II型绫波级驱逐舰一番舰 绫波 （柚） IJN Ayanami 綾波", 
        "猫鲨级潜艇 鲦鱼 USS Dace デイス", 
        "格里德利级驱逐舰4号舰 莫里 USS Maury モーリー", 
        "J级驱逐舰8号舰 标枪 HMS Javelin ジャベリン", 
        "本森级驱逐舰7号舰 拉菲 USS Laffey ラフィー", 
        "阳炎级驱逐舰十五番舰 野分 （苓） IJN Nowaki 野分", 
        "M级驱逐舰 无敌 HMS Matchless マッチレス", 
        "巡潜乙型潜水艇 伊26 IJN I26 イ26", 
        "巡潜乙型改二型潜水艇 伊58 IJN I58 イ58", 
        "1936A型驱逐舰 Z23 KMS Z23 Z23", 
        "1936A型驱逐舰 Z25 KMS Z25 Z25", 
        "1936B型驱逐舰 Z35 KMS Z35 Z35", 
        "东煌海军第一舰队 逸仙 ROC Yat Sen 逸仙", 
        "宁海级轻巡洋舰2号舰 平海 ROC Ping Hai 平海", 
        "宁海级轻巡洋舰1号舰 宁海 ROC Ning Hai 寧海", 
        "司战女神级轻型巡洋舰 黑太子 HMS Black Prince ブラック・プリンス", 
        "黑暗界级浅水重炮舰1号舰 黑暗界 HMS Erebus エレバス", 
        "黑暗界级浅水重炮舰2号舰 恐怖 HMS Terror テラー", 
        "罗伯茨级浅水重炮舰2号舰 阿贝克隆比 HMS Abercrombie アバークロンビー", 
        "布鲁克林级轻巡洋舰9号舰 小海伦娜 Lena リトル・ヘレナ", 
        "实验型轻巡洋舰 夕张 （狐） IJN Yūbari 夕張", 
        "布鲁克林级轻巡洋舰9号舰 海伦娜 USS Helena ヘレナ", 
        "布鲁克林级轻巡洋舰8号舰 圣路易斯 USS St. Louis セントルイス", 
        "阿瑞托莎级轻巡洋舰4号舰 欧若拉 HMS Aurora オーロラ", 
        "克利夫兰级轻巡洋舰1号舰 小克利夫兰 Clevelad リトル・クリーブランド", 
        "克利夫兰级轻巡洋舰1号舰 克利夫兰 USS Cleveland クリーブランド", 
        "克利夫兰级轻巡洋舰4号舰 丹佛 USS Denver デンバー", 
        "爱丁堡级轻型巡洋舰 爱丁堡 HMS Edinburgh エディンバラ", 
        "爱丁堡级轻巡洋舰 小贝法 Little Bel ベルちゃん", 
        "南安普敦级轻巡洋舰 谢菲尔德 HMS Sheffield シェフィールド", 
        "伦敦级重巡洋舰1号舰 伦敦 HMS London ロンドン", 
        "诺福克级重型巡洋舰 多塞特郡 HMS Dorsetshire ドーセットシャー", 
        "北安普顿级重巡洋舰5号舰 休斯敦 USS Houston ヒューストン", 
        "约克级重巡洋舰1号舰 约克 HMS York ヨーク", 
        "约克级重巡洋舰2号舰 埃克塞特 HMS Exeter エクセター", 
        "波特兰级重型巡洋舰2号舰 印第安纳波利斯 USS Indianapolis インディアナポリス", 
        "德意志级装甲舰A号舰 德意志 KMS Deutschland ドイッチュラント", 
        "德意志级装甲舰C号舰 斯佩伯爵海军上将 KMS Admiral Graf.Spee アドミラル・グラーフ・シュペー", 
        "维修舰 女灶神 USS Vestal ヴェスタル", 
        "希佩尔海军上将级重巡洋舰1号舰 希佩尔海军上将 KMS Admiral Hipper アドミラル・ヒッパー", 
        "攻击者级护航航空母舰3号舰 追赶者 HMS Chaser チェイサー", 
        "轻型航空母舰 独角兽 HMS Unicorn ユニコーン", 
        "威奇塔级重巡洋舰 威奇塔 USS Wichita ウィチタ", 
        "列克星敦级航空母舰1号舰 列克星敦 USS Lexington レキシントン", 
        "列克星敦级航空母舰2号舰 萨拉托加 USS Saratoga サラトガ", 
        "勇敢级航空母舰2号舰 光荣 HMS Glorious グロリアス", 
        "航空母舰 皇家方舟 HMS Ark Royal アーク・ロイヤル", 
        "伊丽莎白女王级战列舰1号舰 伊丽莎白女王 HMS Queen Elizabeth クイーン・エリザベス", 
        "声望级战列巡洋舰1号舰 声望 HMS Renown レナウン", 
        "宾夕法尼亚级战列舰2号舰 亚利桑那 USS Arizona アリゾナ", 
        "金刚级高速战舰四番舰 雾岛 （鳗） IJN Kirishima 霧島", 
        "约克城级航空母舰1号舰 约克城 USS Yorktown ヨークタウン", 
        "约克城级航空母舰3号舰 大黄蜂 USS Hornet ホーネット", 
        "纳尔逊级战列舰2号舰 罗德尼 HMS Rodney ロドニー", 
        "纳尔逊级战列舰1号舰 纳尔逊 HMS Nelson ネルソン" 
    ],
    "常驻SSR级舰娘": [ 
        "VIIB型潜艇 U-47 KMS U-47", 
        "VIIC型潜艇 U-81 KMS U-81", 
        "阳炎级驱逐舰八番舰 雪风 （莲） IJN Yukikaze 雪風", 
        "巡潜乙型潜水艇 伊19 IJN I19 イ19", 
        "1936C型驱逐舰 Z46 KMS Z46 Z46", 
        "黛朵级轻巡洋舰8号舰 天狼星 HMS Sirius シリアス", 
        "亚特兰大级轻巡洋舰3号舰 圣地亚哥 USS San Diego サンディエゴ", 
        "克利夫兰级轻巡洋舰3号舰 蒙彼利埃 USS Montpelier モントピリア", 
        "爱丁堡级轻型巡洋舰 贝尔法斯特 HMS Belfast ベルファスト", 
        "确捷级轻巡洋舰 确捷 HMS Swiftsure スウィフトシュア", 
        "维修舰 明石 （茗） IJN Akashi 明石", 
        "希佩尔海军上将级重巡洋舰3号舰 欧根亲王 KMS Prinz Eugen プリンツ・オイゲン", 
        "高雄级重巡洋舰一番舰 高雄 （獒） IJN Takao 高雄", 
        "高雄级重巡洋舰二番舰 爱宕 （犬） IJN Atago 愛宕", 
        "半人马级航空母舰1号舰 半人马 HMS Centaur セントー", 
        "伊丽莎白女王级战列舰2号舰 厌战 HMS Warspite ウォースパイト", 
        "约克城级航空母舰2号舰 企业 USS Enterprise エンタープライズ", 
        "光辉级装甲航空母舰1号舰 光辉 HMS Illustrious イラストリアス", 
        "光辉级装甲航空母舰2号舰 胜利 HMS Victorious ヴィクトリアス", 
        "翔鹤级航空母舰一番舰 翔鹤 （鹬） IJN Shōkaku 翔鶴", 
        "翔鹤级航空母舰二番舰 瑞鹤 （鹤） IJN Zuikaku 瑞鶴", 
        "航空母舰 齐柏林伯爵 KMS Graf Zeppelin グラーフ・ツェッペリン", 
        "装甲航空母舰 大凤 （鹩） IJN Taihō 大鳳", 
        "乔治五世级战列舰3号舰 约克公爵 HMS Duke of York デューク・オブ・ヨーク", 
        "乔治五世级战列舰2号舰 威尔士亲王 HMS Prince of Wales プリンス・オブ・ウェールズ", 
        "海军上将级战列巡洋舰1号舰 胡德 HMS Hood フッド", 
        "俾斯麦级战列舰2号舰 提尔比茨 KMS Tirpitz ティルピッツ" 
    ],
    "碧蓝毒池": [ 
        "SSR级：{%SSR级舰娘}", 
        "SSR级：{%SSR级舰娘}",
        "SR级：{%SR级舰娘}",
        "SR级：{%SR级舰娘}",
        "SR级：{%SR级舰娘}",
        "SR级：{%SR级舰娘}",
        "SR级：{%SR级舰娘}",
        "SR级：{%SR级舰娘}",
        "SR级：{%SR级舰娘}",
        "R级：{%R级舰娘}",
        "R级：{%R级舰娘}",
        "R级：{%R级舰娘}",
        "R级：{%R级舰娘}",
        "R级：{%R级舰娘}",
        "R级：{%R级舰娘}",
        "R级：{%R级舰娘}",
        "R级：{%R级舰娘}",
        "R级：{%R级舰娘}",
        "R级：{%R级舰娘}",
        "R级：{%R级舰娘}",
        "R级：{%R级舰娘}",
        "R级：{%R级舰娘}",
        "R级：{%R级舰娘}",
        "R级：{%R级舰娘}",
        "R级：{%R级舰娘}",
        "R级：{%R级舰娘}",
        "R级：{%R级舰娘}",
        "R级：{%R级舰娘}",
        "N级：{%N级舰娘}",
        "N级：{%N级舰娘}",
        "N级：{%N级舰娘}",
        "N级：{%N级舰娘}",
        "N级：{%N级舰娘}",
        "N级：{%N级舰娘}",
        "N级：{%N级舰娘}",
        "N级：{%N级舰娘}",
        "N级：{%N级舰娘}",
        "N级：{%N级舰娘}",
        "N级：{%N级舰娘}",
        "N级：{%N级舰娘}",
        "N级：{%N级舰娘}",
        "N级：{%N级舰娘}",
        "N级：{%N级舰娘}",
        "N级：{%N级舰娘}",
        "N级：{%N级舰娘}",
        "N级：{%N级舰娘}",
        "N级：{%N级舰娘}",
        "N级：{%N级舰娘}",
        "N级：{%N级舰娘}",
        "N级：{%N级舰娘}",
        "N级：{%N级舰娘}",
        "N级：{%N级舰娘}",
        "N级：{%N级舰娘}",
        "N级：{%N级舰娘}",
        "N级：{%N级舰娘}",
        "N级：{%N级舰娘}",
        "N级：{%N级舰娘}",
        "N级：{%N级舰娘}",
        "N级：{%N级舰娘}",
        "N级：{%N级舰娘}" 
    ],
    "日常捞船": [ 
        "{%碧蓝毒池}"
    ],
    "碧蓝大建": [ 
        "{%日常捞船}\n{%日常捞船}\n{%日常捞船}\n{%日常捞船}\n{%日常捞船}\n{%日常捞船}\n{%日常捞船}\n{%日常捞船}\n{%日常捞船}\n{%日常捞船}",
        "{%日常捞船}\n{%日常捞船}\n{%日常捞船}\n{%日常捞船}\n{%日常捞船}\n{%日常捞船}\n{%日常捞船}\n{%日常捞船}\n{%日常捞船}\n{%日常捞船}",
        "{%日常捞船}\n{%日常捞船}\n{%日常捞船}\n{%日常捞船}\n{%日常捞船}\n{%日常捞船}\n{%日常捞船}\n{%日常捞船}\n{%日常捞船}\n{%日常捞船}",
        "{%日常捞船}\n{%日常捞船}\n{%日常捞船}\n{%日常捞船}\n{%日常捞船}\n{%日常捞船}\n{%日常捞船}\n{%日常捞船}\n{%日常捞船}\n{%日常捞船}",
        "{%日常捞船}\n{%日常捞船}\n{%日常捞船}\n{%日常捞船}\n{%日常捞船}\n{%日常捞船}\n{%日常捞船}\n{%日常捞船}\n{%日常捞船}\n{%日常捞船}",
        "{%日常捞船}\n{%日常捞船}\n{%日常捞船}\n{%日常捞船}\n{%日常捞船}\n{%日常捞船}\n{%日常捞船}\n{%日常捞船}\n{%日常捞船}\n{%日常捞船}",
        "{%日常捞船}\n{%日常捞船}\n{%日常捞船}\n{%日常捞船}\n{%日常捞船}\n{%日常捞船}\n{%日常捞船}\n{%日常捞船}\n{%日常捞船}\n{%日常捞船}",
        "{%日常捞船}\n{%日常捞船}\n{%日常捞船}\n{%日常捞船}\n{%日常捞船}\n{%日常捞船}\n{%日常捞船}\n{%日常捞船}\n{%日常捞船}\n{%日常捞船}",
        "{%日常捞船}\n{%日常捞船}\n{%日常捞船}\n{%日常捞船}\n{%日常捞船}\n{%日常捞船}\n{%日常捞船}\n{%日常捞船}\n{%日常捞船}\n{%日常捞船}",
        "{%日常捞船}\n{%日常捞船}\n{%日常捞船}\n{%日常捞船}\n{%日常捞船}\n{%日常捞船}\n{%日常捞船}\n{%日常捞船}\n{%日常捞船}\n{%日常捞船}" 
    ],
    "十发大建": [
        "{%碧蓝大建}"
    ]
}
